cochlea/__init__.py
cochlea/asr/holmberg2007.csv
cochlea/asr/matlab_auditory_periphery.csv
cochlea/asr/zilany2014.csv
cochlea/asr/__init__.py
cochlea/external/__init__.py
cochlea/external/matlab_auditory_periphery/__init__.py
cochlea/holmberg2007/bm_pars.py
cochlea/holmberg2007/traveling_waves.py
cochlea/holmberg2007/_traveling_waves.pyd
cochlea/holmberg2007/__init__.py
cochlea/stats/isointensity.py
cochlea/stats/modulation_gain.py
cochlea/stats/rate_intensity.py
cochlea/stats/rate_level.py
cochlea/stats/synchronization.py
cochlea/stats/threshold_rate.py
cochlea/stats/threshold_si.py
cochlea/stats/tuning.py
cochlea/stats/__init__.py
cochlea/zilany2009/ffGn_module.py
cochlea/zilany2009/_pycat.pyd
cochlea/zilany2009/__init__.py
cochlea/zilany2014/util.py
cochlea/zilany2014/zilany2014_rate.py
cochlea/zilany2014/_zilany2014.pyd
cochlea/zilany2014/__init__.py
cochlea-1.2.data/scripts/run_zilany2014
cochlea-1.2.dist-info/DESCRIPTION.rst
cochlea-1.2.dist-info/METADATA
cochlea-1.2.dist-info/metadata.json
cochlea-1.2.dist-info/RECORD
cochlea-1.2.dist-info/top_level.txt
cochlea-1.2.dist-info/WHEEL
