Metadata-Version: 2.0
Name: cochlea
Version: 1.2
Summary: Inner ear models in Python
Home-page: https://github.com/mrkrd/cochlea
Author: Marek Rudnicki
Author-email: marek.rudnicki@tum.de
License: GPLv3+
Download-URL: https://github.com/mrkrd/cochlea/tarball/master
Platform: Linux
Platform: Windows
Platform: FreeBSD
Platform: OSX
Classifier: Development Status :: 5 - Production/Stable
Classifier: Environment :: Console
Classifier: Intended Audience :: Science/Research
Classifier: License :: OSI Approved :: GNU General Public License v3 or later (GPLv3+)
Classifier: Operating System :: POSIX
Classifier: Operating System :: Microsoft :: Windows
Classifier: Operating System :: MacOS :: MacOS X
Classifier: Programming Language :: Python
Classifier: Programming Language :: Python :: 2.7
Classifier: Programming Language :: Cython
Classifier: Programming Language :: C
Requires-Dist: numpy
Requires-Dist: pandas
Requires-Dist: scipy
